soccminer/__init__.py
soccminer/comments.py
soccminer/comments_miner.py
soccminer/environment.py
soccminer/exception_monitoring.py
soccminer/helper.py
soccminer/java_ast_parsing.py
soccminer/java_proj_miner.py
soccminer/java_project_meta_attributes.py
soccminer/json_serialization.py
soccminer/parse_source_files.py
soccminer/performance_time.py
soccminer/process_parameters.py
soccminer/proj_comments_comprehensive_attr.py
soccminer/proj_comments_main_attr.py
soccminer/project_attributes.py
soccminer/project_meta.py
soccminer/soccminer_logger.py
soccminer/source_code_details.py
soccminer/srcml.py
soccminer-0.0.43a1.data/scripts/main.py
soccminer-0.0.43a1.dist-info/LICENSE
soccminer-0.0.43a1.dist-info/METADATA
soccminer-0.0.43a1.dist-info/WHEEL
soccminer-0.0.43a1.dist-info/top_level.txt
soccminer-0.0.43a1.dist-info/RECORD
